README.md
setup.py
kvdb/__init__.py
kvdb/kv.py
kvdb.egg-info/PKG-INFO
kvdb.egg-info/SOURCES.txt
kvdb.egg-info/dependency_links.txt
kvdb.egg-info/requires.txt
kvdb.egg-info/top_level.txt