Metadata-Version: 1.0
Name: kvdb
Version: 2
Summary: Key-Value-Database
Home-page: https://github.com/rcbensley/mariadb-dba/kvdb
Author: UNKNOWN
Author-email: UNKNOWN
License: UNKNOWN
Keywords: kvdb
Platform: UNKNOWN
